<?xml version="1.0" encoding="utf-8"?>
<data>
  <defaultadtitle>更多合作细节，请联系Mr.Jailu@gmail.com。</defaultadtitle>
  <defaultadurl>mailto:mr.jailu@gmail.com</defaultadurl>
  <StartAdFormDisplayedProbability>3</StartAdFormDisplayedProbability>
  <IsDisplayedStartAdForm>1</IsDisplayedStartAdForm>
  <StartAdFormPageUrl>http://jailu.cn/xmanad.htm</StartAdFormPageUrl>
  <TopAd>单品团购，一网打尽</TopAd>
  <TopAdLink>http://www.78gw.com?f=cafe</TopAdLink>
  <AddMe>1</AddMe>
  <version>
    <last>2010072302</last>
    <last1>2010072302</last1>
    <file>http://kaixin001-helper.googlecode.com/files/XMan_Build_2010072302.zip</file>
    <size>259721</size>
    <name>X超人 Build 20100723</name>
    <publisheddate>2010-07-23</publisheddate>
    <whatsnew>
      <![CDATA[
Kaixin001.XMan.Build 20100723 What's New:
＝＝＝＝＝＝＝＝＝＝＝＝＝＝＝＝＝＝＝＝＝＝＝＝＝＝＝＝＝＝

1. 修正：官方调整后，经验溢出当前升级经验后,X-Man会反复做同一个任务的Bug


Kaixin001.XMan.Build 20100723 What's New:
＝＝＝＝＝＝＝＝＝＝＝＝＝＝＝＝＝＝＝＝＝＝＝＝＝＝＝＝＝＝

1. 新增：用光能量再升级功能，最大限度上减少升级时能量值的浪费

2. 新增：不再重复挑战挑战失败的对手，提高挑战成功率

3. 修正：某些情况下，X-Man对现金、能量、战斗等值计算错误的问题

4. 修正：某些情况下，某些帐号无法自动领取先知150/200能量包的问题

5. 修正：现金过大时，X-Man显示现金为0的Bug
      ]]>
    </whatsnew>
  </version>
  <ads>
    <ad>
      <title>
        20100105版农夫新增强制防大兵成龙功能，请及时更新！
      </title>
      <url>
        http://bbs.snsfun.com/thread-82550-1-1.html
      </url>
      <color>-65408</color>
      <expired>2019-12-13 23:59:59</expired>
    </ad>
  </ads>
  <ads1>
    <ad>
      <title>
        点击下载最新版开心车夫，修正老版本不加油等问题
      </title>
      <url>
        http://bbs.snsfun.com/viewthread.php?tid=74889
      </url>
      <color>-16744448</color>
      <expired>2019-11-08 11:13:00</expired>
    </ad>
  </ads1>
  <fund>
    http://www.cnblogs.com/jailu/archive/2009/08/23/1552371.html
  </fund>
</data>